{
  "_meta": {
    "folder": "Paris-ST",
    "last_scan": "2026-04-30",
    "thumbnail_source": "origin/thumbnail"
  },
  "processed": [
    "Paris-ST/R0010643.jpeg",
    "Paris-ST/R0010645.jpeg",
    "Paris-ST/R0010648.jpeg",
    "Paris-ST/R0011041.jpeg",
    "Paris-ST/R0011197.jpeg",
    "Paris-ST/R0011272.jpeg",
    "Paris-ST/R0011297.jpeg",
    "Paris-ST/R0011374.jpeg",
    "Paris-ST/R0011385.jpeg",
    "Paris-ST/R0011461.jpeg",
    "Paris-ST/R0011477.jpeg",
    "Paris-ST/R0011517.jpeg",
    "Paris-ST/R0011574.jpeg",
    "Paris-ST/R0011597.jpeg",
    "Paris-ST/R0011625.jpeg",
    "Paris-ST/R0011640.jpeg",
    "Paris-ST/R0011758.jpeg",
    "Paris-ST/R0011795.jpeg",
    "Paris-ST/R0011797.jpeg",
    "Paris-ST/R0011982.jpeg"
  ]
}
